{"city": "Delhi", "timestamp": "2026-01-10T16:48:38.776735", "temp": 20.2, "temp_min": 20.2, "temp_max": 20.2, "humidity": 30, "pressure": 1017, "rain_1h": 0, "rain_3h": 0, "wind_speed": 2.95, "clouds": 0, "weather": "Clear", "description": "clear sky", "collected_at": "2026-01-10T16:48:48.942793"}
{"city": "Mumbai", "timestamp": "2026-01-10T16:48:39.731272", "temp": 24.19, "temp_min": 24.19, "temp_max": 24.19, "humidity": 57, "pressure": 1013, "rain_1h": 0, "rain_3h": 0, "wind_speed": 9.74, "clouds": 1, "weather": "Clear", "description": "clear sky", "collected_at": "2026-01-10T16:48:48.943154"}
{"city": "Chennai", "timestamp": "2026-01-10T16:48:40.620640", "temp": 24.41, "temp_min": 24.41, "temp_max": 24.41, "humidity": 72, "pressure": 1012, "rain_1h": 0, "rain_3h": 0, "wind_speed": 7.85, "clouds": 100, "weather": "Clouds", "description": "overcast clouds", "collected_at": "2026-01-10T16:48:48.943203"}
{"city": "Bangalore", "timestamp": "2026-01-10T16:48:41.485896", "temp": 21.41, "temp_min": 21.41, "temp_max": 21.41, "humidity": 63, "pressure": 1013, "rain_1h": 0, "rain_3h": 0, "wind_speed": 3.68, "clouds": 100, "weather": "Clouds", "description": "overcast clouds", "collected_at": "2026-01-10T16:48:48.943236"}
{"city": "Kolkata", "timestamp": "2026-01-10T16:48:42.464137", "temp": 23.46, "temp_min": 23.46, "temp_max": 23.46, "humidity": 23, "pressure": 1014, "rain_1h": 0, "rain_3h": 0, "wind_speed": 3.65, "clouds": 7, "weather": "Clear", "description": "clear sky", "collected_at": "2026-01-10T16:48:48.943266"}
{"city": "Pune", "timestamp": "2026-01-10T16:48:43.353926", "temp": 27.61, "temp_min": 27.61, "temp_max": 27.61, "humidity": 23, "pressure": 1013, "rain_1h": 0, "rain_3h": 0, "wind_speed": 2.19, "clouds": 14, "weather": "Clouds", "description": "few clouds", "collected_at": "2026-01-10T16:48:48.943293"}
{"city": "Hyderabad", "timestamp": "2026-01-10T16:48:44.320672", "temp": 23.04, "temp_min": 23.04, "temp_max": 23.04, "humidity": 29, "pressure": 1014, "rain_1h": 0, "rain_3h": 0, "wind_speed": 2.26, "clouds": 74, "weather": "Clouds", "description": "broken clouds", "collected_at": "2026-01-10T16:48:48.943471"}
{"city": "Ahmedabad", "timestamp": "2026-01-10T16:48:45.199375", "temp": 25.29, "temp_min": 25.29, "temp_max": 25.29, "humidity": 21, "pressure": 1015, "rain_1h": 0, "rain_3h": 0, "wind_speed": 3.86, "clouds": 0, "weather": "Clear", "description": "clear sky", "collected_at": "2026-01-10T16:48:48.943508"}
{"city": "Coimbatore", "timestamp": "2026-01-10T16:48:46.071141", "temp": 24.49, "temp_min": 24.49, "temp_max": 24.49, "humidity": 64, "pressure": 1011, "rain_1h": 0, "rain_3h": 0, "wind_speed": 3.84, "clouds": 100, "weather": "Clouds", "description": "overcast clouds", "collected_at": "2026-01-10T16:48:48.943535"}
{"city": "Madurai", "timestamp": "2026-01-10T16:48:46.968680", "temp": 24.05, "temp_min": 24.05, "temp_max": 24.05, "humidity": 73, "pressure": 1011, "rain_1h": 0, "rain_3h": 0, "wind_speed": 3.52, "clouds": 99, "weather": "Clouds", "description": "overcast clouds", "collected_at": "2026-01-10T16:48:48.943561"}
{"city": "Visakhapatnam", "timestamp": "2026-01-10T16:48:47.859777", "temp": 23.63, "temp_min": 23.63, "temp_max": 23.63, "humidity": 39, "pressure": 1014, "rain_1h": 0, "rain_3h": 0, "wind_speed": 3.8, "clouds": 81, "weather": "Clouds", "description": "broken clouds", "collected_at": "2026-01-10T16:48:48.943586"}
{"city": "Vijayawada", "timestamp": "2026-01-10T16:48:48.793661", "temp": 21.83, "temp_min": 21.83, "temp_max": 21.83, "humidity": 51, "pressure": 1014, "rain_1h": 0, "rain_3h": 0, "wind_speed": 1.66, "clouds": 95, "weather": "Clouds", "description": "overcast clouds", "collected_at": "2026-01-10T16:48:48.943611"}
{"city": "Delhi", "timestamp": "2026-01-29T12:42:27.301958", "temp": 13.05, "temp_min": 13.05, "temp_max": 13.05, "humidity": 88, "pressure": 1020, "rain_1h": 0, "rain_3h": 0, "wind_speed": 3.09, "clouds": 20, "weather": "Mist", "description": "mist", "collected_at": "2026-01-29T12:42:32.069167"}
{"city": "Mumbai", "timestamp": "2026-01-29T12:42:27.737487", "temp": 30.99, "temp_min": 27.94, "temp_max": 30.99, "humidity": 40, "pressure": 1014, "rain_1h": 0, "rain_3h": 0, "wind_speed": 4.12, "clouds": 0, "weather": "Smoke", "description": "smoke", "collected_at": "2026-01-29T12:42:32.069205"}
{"city": "Chennai", "timestamp": "2026-01-29T12:42:28.152415", "temp": 28.39, "temp_min": 27.83, "temp_max": 29.57, "humidity": 60, "pressure": 1016, "rain_1h": 0, "rain_3h": 0, "wind_speed": 5.14, "clouds": 40, "weather": "Haze", "description": "haze", "collected_at": "2026-01-29T12:42:32.069221"}
{"city": "Bangalore", "timestamp": "2026-01-29T12:42:28.564034", "temp": 25.68, "temp_min": 24.8, "temp_max": 26.4, "humidity": 43, "pressure": 1015, "rain_1h": 0, "rain_3h": 0, "wind_speed": 10.28, "clouds": 0, "weather": "Clear", "description": "clear sky", "collected_at": "2026-01-29T12:42:32.069233"}
{"city": "Kolkata", "timestamp": "2026-01-29T12:42:29.003281", "temp": 25.97, "temp_min": 25.97, "temp_max": 25.97, "humidity": 36, "pressure": 1015, "rain_1h": 0, "rain_3h": 0, "wind_speed": 4.12, "clouds": 0, "weather": "Haze", "description": "haze", "collected_at": "2026-01-29T12:42:32.069243"}
{"city": "Pune", "timestamp": "2026-01-29T12:42:29.414579", "temp": 26.89, "temp_min": 26.89, "temp_max": 26.89, "humidity": 42, "pressure": 1015, "rain_1h": 0, "rain_3h": 0, "wind_speed": 3.86, "clouds": 82, "weather": "Clouds", "description": "broken clouds", "collected_at": "2026-01-29T12:42:32.069252"}
{"city": "Hyderabad", "timestamp": "2026-01-29T12:42:29.835534", "temp": 27.23, "temp_min": 27.23, "temp_max": 28.73, "humidity": 44, "pressure": 1015, "rain_1h": 0, "rain_3h": 0, "wind_speed": 5.14, "clouds": 40, "weather": "Haze", "description": "haze", "collected_at": "2026-01-29T12:42:32.069261"}
{"city": "Ahmedabad", "timestamp": "2026-01-29T12:42:30.255949", "temp": 23.02, "temp_min": 23.02, "temp_max": 23.02, "humidity": 40, "pressure": 1017, "rain_1h": 0, "rain_3h": 0, "wind_speed": 4.12, "clouds": 99, "weather": "Smoke", "description": "smoke", "collected_at": "2026-01-29T12:42:32.069286"}
{"city": "Coimbatore", "timestamp": "2026-01-29T12:42:30.683927", "temp": 27.88, "temp_min": 27.88, "temp_max": 27.88, "humidity": 39, "pressure": 1015, "rain_1h": 0, "rain_3h": 0, "wind_speed": 3.6, "clouds": 40, "weather": "Haze", "description": "haze", "collected_at": "2026-01-29T12:42:32.069294"}
{"city": "Madurai", "timestamp": "2026-01-29T12:42:31.094374", "temp": 30.01, "temp_min": 30.01, "temp_max": 30.01, "humidity": 51, "pressure": 1014, "rain_1h": 0, "rain_3h": 0, "wind_speed": 5.14, "clouds": 20, "weather": "Haze", "description": "haze", "collected_at": "2026-01-29T12:42:32.069303"}
{"city": "Visakhapatnam", "timestamp": "2026-01-29T12:42:31.515018", "temp": 28.94, "temp_min": 28.94, "temp_max": 28.94, "humidity": 51, "pressure": 1015, "rain_1h": 0, "rain_3h": 0, "wind_speed": 4.12, "clouds": 20, "weather": "Haze", "description": "haze", "collected_at": "2026-01-29T12:42:32.069310"}
{"city": "Vijayawada", "timestamp": "2026-01-29T12:42:31.923040", "temp": 26.97, "temp_min": 26.97, "temp_max": 26.97, "humidity": 57, "pressure": 1015, "rain_1h": 0, "rain_3h": 0, "wind_speed": 2.06, "clouds": 40, "weather": "Haze", "description": "haze", "collected_at": "2026-01-29T12:42:32.069318"}
{"city": "Delhi", "timestamp": "2026-01-29T12:42:44.745319", "temp": 13.05, "temp_min": 13.05, "temp_max": 13.05, "humidity": 88, "pressure": 1020, "rain_1h": 0, "rain_3h": 0, "wind_speed": 3.09, "clouds": 20, "weather": "Mist", "description": "mist", "collected_at": "2026-01-29T12:42:49.299039"}
{"city": "Mumbai", "timestamp": "2026-01-29T12:42:45.146220", "temp": 30.99, "temp_min": 27.94, "temp_max": 30.99, "humidity": 40, "pressure": 1014, "rain_1h": 0, "rain_3h": 0, "wind_speed": 4.12, "clouds": 0, "weather": "Smoke", "description": "smoke", "collected_at": "2026-01-29T12:42:49.299067"}
{"city": "Chennai", "timestamp": "2026-01-29T12:42:45.553304", "temp": 28.39, "temp_min": 27.83, "temp_max": 29.57, "humidity": 60, "pressure": 1016, "rain_1h": 0, "rain_3h": 0, "wind_speed": 5.14, "clouds": 40, "weather": "Haze", "description": "haze", "collected_at": "2026-01-29T12:42:49.299081"}
{"city": "Bangalore", "timestamp": "2026-01-29T12:42:45.984850", "temp": 25.79, "temp_min": 24.64, "temp_max": 26.4, "humidity": 44, "pressure": 1015, "rain_1h": 0, "rain_3h": 0, "wind_speed": 10.28, "clouds": 0, "weather": "Clear", "description": "clear sky", "collected_at": "2026-01-29T12:42:49.299092"}
{"city": "Kolkata", "timestamp": "2026-01-29T12:42:46.391478", "temp": 25.97, "temp_min": 25.97, "temp_max": 25.97, "humidity": 36, "pressure": 1015, "rain_1h": 0, "rain_3h": 0, "wind_speed": 4.12, "clouds": 0, "weather": "Haze", "description": "haze", "collected_at": "2026-01-29T12:42:49.299101"}
{"city": "Pune", "timestamp": "2026-01-29T12:42:46.825111", "temp": 26.89, "temp_min": 26.89, "temp_max": 26.89, "humidity": 42, "pressure": 1015, "rain_1h": 0, "rain_3h": 0, "wind_speed": 3.86, "clouds": 82, "weather": "Clouds", "description": "broken clouds", "collected_at": "2026-01-29T12:42:49.299109"}
{"city": "Hyderabad", "timestamp": "2026-01-29T12:42:47.236451", "temp": 27.23, "temp_min": 27.23, "temp_max": 28.73, "humidity": 44, "pressure": 1015, "rain_1h": 0, "rain_3h": 0, "wind_speed": 5.14, "clouds": 40, "weather": "Haze", "description": "haze", "collected_at": "2026-01-29T12:42:49.299117"}
{"city": "Ahmedabad", "timestamp": "2026-01-29T12:42:47.625990", "temp": 23.02, "temp_min": 23.02, "temp_max": 23.02, "humidity": 40, "pressure": 1017, "rain_1h": 0, "rain_3h": 0, "wind_speed": 4.12, "clouds": 99, "weather": "Smoke", "description": "smoke", "collected_at": "2026-01-29T12:42:49.299125"}
{"city": "Coimbatore", "timestamp": "2026-01-29T12:42:48.035332", "temp": 27.88, "temp_min": 27.88, "temp_max": 27.88, "humidity": 39, "pressure": 1015, "rain_1h": 0, "rain_3h": 0, "wind_speed": 3.6, "clouds": 40, "weather": "Haze", "description": "haze", "collected_at": "2026-01-29T12:42:49.299133"}
{"city": "Madurai", "timestamp": "2026-01-29T12:42:48.457398", "temp": 30.01, "temp_min": 30.01, "temp_max": 30.01, "humidity": 51, "pressure": 1014, "rain_1h": 0, "rain_3h": 0, "wind_speed": 5.14, "clouds": 20, "weather": "Haze", "description": "haze", "collected_at": "2026-01-29T12:42:49.299141"}
{"city": "Visakhapatnam", "timestamp": "2026-01-29T12:42:48.864974", "temp": 28.94, "temp_min": 28.94, "temp_max": 28.94, "humidity": 51, "pressure": 1015, "rain_1h": 0, "rain_3h": 0, "wind_speed": 4.12, "clouds": 20, "weather": "Haze", "description": "haze", "collected_at": "2026-01-29T12:42:49.299149"}
{"city": "Vijayawada", "timestamp": "2026-01-29T12:42:49.264009", "temp": 26.97, "temp_min": 26.97, "temp_max": 26.97, "humidity": 57, "pressure": 1015, "rain_1h": 0, "rain_3h": 0, "wind_speed": 2.06, "clouds": 40, "weather": "Haze", "description": "haze", "collected_at": "2026-01-29T12:42:49.299157"}
{"city": "Delhi", "timestamp": "2026-01-29T12:43:01.281069", "temp": 13.05, "temp_min": 13.05, "temp_max": 13.05, "humidity": 88, "pressure": 1020, "rain_1h": 0, "rain_3h": 0, "wind_speed": 3.09, "clouds": 20, "weather": "Mist", "description": "mist", "collected_at": "2026-01-29T12:43:05.996257"}
{"city": "Mumbai", "timestamp": "2026-01-29T12:43:01.700921", "temp": 30.99, "temp_min": 27.94, "temp_max": 30.99, "humidity": 40, "pressure": 1014, "rain_1h": 0, "rain_3h": 0, "wind_speed": 4.12, "clouds": 0, "weather": "Smoke", "description": "smoke", "collected_at": "2026-01-29T12:43:05.996284"}
{"city": "Chennai", "timestamp": "2026-01-29T12:43:02.125130", "temp": 28.39, "temp_min": 27.83, "temp_max": 29.57, "humidity": 60, "pressure": 1016, "rain_1h": 0, "rain_3h": 0, "wind_speed": 5.14, "clouds": 40, "weather": "Haze", "description": "haze", "collected_at": "2026-01-29T12:43:05.996299"}
{"city": "Bangalore", "timestamp": "2026-01-29T12:43:02.540942", "temp": 25.79, "temp_min": 24.64, "temp_max": 26.4, "humidity": 44, "pressure": 1015, "rain_1h": 0, "rain_3h": 0, "wind_speed": 10.28, "clouds": 0, "weather": "Clear", "description": "clear sky", "collected_at": "2026-01-29T12:43:05.996310"}
{"city": "Kolkata", "timestamp": "2026-01-29T12:43:02.947475", "temp": 25.97, "temp_min": 25.97, "temp_max": 25.97, "humidity": 36, "pressure": 1015, "rain_1h": 0, "rain_3h": 0, "wind_speed": 4.12, "clouds": 0, "weather": "Haze", "description": "haze", "collected_at": "2026-01-29T12:43:05.996319"}
{"city": "Pune", "timestamp": "2026-01-29T12:43:03.387768", "temp": 26.89, "temp_min": 26.89, "temp_max": 26.89, "humidity": 42, "pressure": 1015, "rain_1h": 0, "rain_3h": 0, "wind_speed": 3.86, "clouds": 82, "weather": "Clouds", "description": "broken clouds", "collected_at": "2026-01-29T12:43:05.996327"}
{"city": "Hyderabad", "timestamp": "2026-01-29T12:43:03.816883", "temp": 27.23, "temp_min": 27.23, "temp_max": 28.73, "humidity": 44, "pressure": 1015, "rain_1h": 0, "rain_3h": 0, "wind_speed": 5.14, "clouds": 40, "weather": "Haze", "description": "haze", "collected_at": "2026-01-29T12:43:05.996335"}
{"city": "Ahmedabad", "timestamp": "2026-01-29T12:43:04.251307", "temp": 23.02, "temp_min": 23.02, "temp_max": 23.02, "humidity": 40, "pressure": 1017, "rain_1h": 0, "rain_3h": 0, "wind_speed": 4.12, "clouds": 99, "weather": "Smoke", "description": "smoke", "collected_at": "2026-01-29T12:43:05.996343"}
{"city": "Coimbatore", "timestamp": "2026-01-29T12:43:04.691176", "temp": 27.88, "temp_min": 27.88, "temp_max": 27.88, "humidity": 39, "pressure": 1015, "rain_1h": 0, "rain_3h": 0, "wind_speed": 3.6, "clouds": 40, "weather": "Haze", "description": "haze", "collected_at": "2026-01-29T12:43:05.996350"}
{"city": "Madurai", "timestamp": "2026-01-29T12:43:05.117615", "temp": 30.01, "temp_min": 30.01, "temp_max": 30.01, "humidity": 51, "pressure": 1014, "rain_1h": 0, "rain_3h": 0, "wind_speed": 5.14, "clouds": 20, "weather": "Haze", "description": "haze", "collected_at": "2026-01-29T12:43:05.996360"}
{"city": "Visakhapatnam", "timestamp": "2026-01-29T12:43:05.540922", "temp": 28.94, "temp_min": 28.94, "temp_max": 28.94, "humidity": 51, "pressure": 1015, "rain_1h": 0, "rain_3h": 0, "wind_speed": 4.12, "clouds": 20, "weather": "Haze", "description": "haze", "collected_at": "2026-01-29T12:43:05.996368"}
{"city": "Vijayawada", "timestamp": "2026-01-29T12:43:05.980361", "temp": 26.97, "temp_min": 26.97, "temp_max": 26.97, "humidity": 57, "pressure": 1015, "rain_1h": 0, "rain_3h": 0, "wind_speed": 2.06, "clouds": 40, "weather": "Haze", "description": "haze", "collected_at": "2026-01-29T12:43:05.996376"}
{"city": "Delhi", "timestamp": "2026-01-29T12:43:17.001162", "temp": 13.05, "temp_min": 13.05, "temp_max": 13.05, "humidity": 88, "pressure": 1020, "rain_1h": 0, "rain_3h": 0, "wind_speed": 3.09, "clouds": 20, "weather": "Mist", "description": "mist", "collected_at": "2026-01-29T12:43:21.658372"}
{"city": "Mumbai", "timestamp": "2026-01-29T12:43:17.441388", "temp": 30.99, "temp_min": 27.94, "temp_max": 30.99, "humidity": 40, "pressure": 1014, "rain_1h": 0, "rain_3h": 0, "wind_speed": 4.12, "clouds": 0, "weather": "Smoke", "description": "smoke", "collected_at": "2026-01-29T12:43:21.658401"}
{"city": "Chennai", "timestamp": "2026-01-29T12:43:17.853088", "temp": 28.39, "temp_min": 27.83, "temp_max": 29.57, "humidity": 60, "pressure": 1016, "rain_1h": 0, "rain_3h": 0, "wind_speed": 5.14, "clouds": 40, "weather": "Haze", "description": "haze", "collected_at": "2026-01-29T12:43:21.658441"}
{"city": "Bangalore", "timestamp": "2026-01-29T12:43:18.247167", "temp": 25.79, "temp_min": 24.64, "temp_max": 26.4, "humidity": 44, "pressure": 1015, "rain_1h": 0, "rain_3h": 0, "wind_speed": 10.28, "clouds": 0, "weather": "Clear", "description": "clear sky", "collected_at": "2026-01-29T12:43:21.658452"}
{"city": "Kolkata", "timestamp": "2026-01-29T12:43:18.666877", "temp": 25.97, "temp_min": 25.97, "temp_max": 25.97, "humidity": 36, "pressure": 1015, "rain_1h": 0, "rain_3h": 0, "wind_speed": 4.12, "clouds": 0, "weather": "Haze", "description": "haze", "collected_at": "2026-01-29T12:43:21.658461"}
{"city": "Pune", "timestamp": "2026-01-29T12:43:19.109476", "temp": 26.89, "temp_min": 26.89, "temp_max": 26.89, "humidity": 42, "pressure": 1015, "rain_1h": 0, "rain_3h": 0, "wind_speed": 3.86, "clouds": 82, "weather": "Clouds", "description": "broken clouds", "collected_at": "2026-01-29T12:43:21.658469"}
{"city": "Hyderabad", "timestamp": "2026-01-29T12:43:19.527320", "temp": 27.23, "temp_min": 27.23, "temp_max": 28.73, "humidity": 44, "pressure": 1015, "rain_1h": 0, "rain_3h": 0, "wind_speed": 5.14, "clouds": 40, "weather": "Haze", "description": "haze", "collected_at": "2026-01-29T12:43:21.658477"}
{"city": "Ahmedabad", "timestamp": "2026-01-29T12:43:19.945443", "temp": 23.02, "temp_min": 23.02, "temp_max": 23.02, "humidity": 40, "pressure": 1017, "rain_1h": 0, "rain_3h": 0, "wind_speed": 4.12, "clouds": 99, "weather": "Smoke", "description": "smoke", "collected_at": "2026-01-29T12:43:21.658485"}
{"city": "Coimbatore", "timestamp": "2026-01-29T12:43:20.444477", "temp": 27.88, "temp_min": 27.88, "temp_max": 27.88, "humidity": 39, "pressure": 1015, "rain_1h": 0, "rain_3h": 0, "wind_speed": 3.6, "clouds": 40, "weather": "Haze", "description": "haze", "collected_at": "2026-01-29T12:43:21.658493"}
{"city": "Madurai", "timestamp": "2026-01-29T12:43:20.835337", "temp": 30.01, "temp_min": 30.01, "temp_max": 30.01, "humidity": 51, "pressure": 1014, "rain_1h": 0, "rain_3h": 0, "wind_speed": 5.14, "clouds": 20, "weather": "Haze", "description": "haze", "collected_at": "2026-01-29T12:43:21.658500"}
{"city": "Visakhapatnam", "timestamp": "2026-01-29T12:43:21.226895", "temp": 28.94, "temp_min": 28.94, "temp_max": 28.94, "humidity": 51, "pressure": 1015, "rain_1h": 0, "rain_3h": 0, "wind_speed": 4.12, "clouds": 20, "weather": "Haze", "description": "haze", "collected_at": "2026-01-29T12:43:21.658508"}
{"city": "Vijayawada", "timestamp": "2026-01-29T12:43:21.640452", "temp": 26.97, "temp_min": 26.97, "temp_max": 26.97, "humidity": 57, "pressure": 1015, "rain_1h": 0, "rain_3h": 0, "wind_speed": 2.06, "clouds": 40, "weather": "Haze", "description": "haze", "collected_at": "2026-01-29T12:43:21.658516"}
{"city": "Delhi", "timestamp": "2026-01-29T12:43:57.633652", "temp": 13.05, "temp_min": 13.05, "temp_max": 13.05, "humidity": 88, "pressure": 1020, "rain_1h": 0, "rain_3h": 0, "wind_speed": 3.09, "clouds": 20, "weather": "Mist", "description": "mist", "collected_at": "2026-01-29T12:44:02.238296"}
{"city": "Mumbai", "timestamp": "2026-01-29T12:43:58.063793", "temp": 30.99, "temp_min": 27.94, "temp_max": 30.99, "humidity": 40, "pressure": 1014, "rain_1h": 0, "rain_3h": 0, "wind_speed": 4.12, "clouds": 0, "weather": "Smoke", "description": "smoke", "collected_at": "2026-01-29T12:44:02.238500"}
{"city": "Chennai", "timestamp": "2026-01-29T12:43:58.461256", "temp": 28.39, "temp_min": 27.83, "temp_max": 29.57, "humidity": 60, "pressure": 1016, "rain_1h": 0, "rain_3h": 0, "wind_speed": 5.14, "clouds": 40, "weather": "Haze", "description": "haze", "collected_at": "2026-01-29T12:44:02.238525"}
{"city": "Bangalore", "timestamp": "2026-01-29T12:43:58.877166", "temp": 25.79, "temp_min": 24.64, "temp_max": 26.4, "humidity": 44, "pressure": 1015, "rain_1h": 0, "rain_3h": 0, "wind_speed": 10.28, "clouds": 0, "weather": "Clear", "description": "clear sky", "collected_at": "2026-01-29T12:44:02.238537"}
{"city": "Kolkata", "timestamp": "2026-01-29T12:43:59.280360", "temp": 25.97, "temp_min": 25.97, "temp_max": 25.97, "humidity": 36, "pressure": 1015, "rain_1h": 0, "rain_3h": 0, "wind_speed": 4.12, "clouds": 0, "weather": "Haze", "description": "haze", "collected_at": "2026-01-29T12:44:02.238546"}
{"city": "Pune", "timestamp": "2026-01-29T12:43:59.666719", "temp": 26.89, "temp_min": 26.89, "temp_max": 26.89, "humidity": 42, "pressure": 1015, "rain_1h": 0, "rain_3h": 0, "wind_speed": 3.86, "clouds": 82, "weather": "Clouds", "description": "broken clouds", "collected_at": "2026-01-29T12:44:02.238555"}
{"city": "Hyderabad", "timestamp": "2026-01-29T12:44:00.070866", "temp": 27.23, "temp_min": 27.23, "temp_max": 28.73, "humidity": 44, "pressure": 1015, "rain_1h": 0, "rain_3h": 0, "wind_speed": 5.14, "clouds": 40, "weather": "Haze", "description": "haze", "collected_at": "2026-01-29T12:44:02.238563"}
{"city": "Ahmedabad", "timestamp": "2026-01-29T12:44:00.515284", "temp": 23.02, "temp_min": 23.02, "temp_max": 23.02, "humidity": 40, "pressure": 1017, "rain_1h": 0, "rain_3h": 0, "wind_speed": 4.12, "clouds": 99, "weather": "Smoke", "description": "smoke", "collected_at": "2026-01-29T12:44:02.238571"}
{"city": "Coimbatore", "timestamp": "2026-01-29T12:44:00.943479", "temp": 27.88, "temp_min": 27.88, "temp_max": 27.88, "humidity": 39, "pressure": 1015, "rain_1h": 0, "rain_3h": 0, "wind_speed": 3.6, "clouds": 40, "weather": "Haze", "description": "haze", "collected_at": "2026-01-29T12:44:02.238579"}
{"city": "Madurai", "timestamp": "2026-01-29T12:44:01.382985", "temp": 30.01, "temp_min": 30.01, "temp_max": 30.01, "humidity": 51, "pressure": 1014, "rain_1h": 0, "rain_3h": 0, "wind_speed": 5.14, "clouds": 20, "weather": "Haze", "description": "haze", "collected_at": "2026-01-29T12:44:02.238587"}
{"city": "Visakhapatnam", "timestamp": "2026-01-29T12:44:01.823096", "temp": 28.94, "temp_min": 28.94, "temp_max": 28.94, "humidity": 51, "pressure": 1015, "rain_1h": 0, "rain_3h": 0, "wind_speed": 4.12, "clouds": 20, "weather": "Haze", "description": "haze", "collected_at": "2026-01-29T12:44:02.238595"}
{"city": "Vijayawada", "timestamp": "2026-01-29T12:44:02.221360", "temp": 26.97, "temp_min": 26.97, "temp_max": 26.97, "humidity": 57, "pressure": 1015, "rain_1h": 0, "rain_3h": 0, "wind_speed": 2.06, "clouds": 40, "weather": "Haze", "description": "haze", "collected_at": "2026-01-29T12:44:02.238602"}
{"city": "Delhi", "timestamp": "2026-01-29T12:44:12.992639", "temp": 13.05, "temp_min": 13.05, "temp_max": 13.05, "humidity": 88, "pressure": 1020, "rain_1h": 0, "rain_3h": 0, "wind_speed": 3.09, "clouds": 20, "weather": "Mist", "description": "mist", "collected_at": "2026-01-29T12:44:17.606998"}
{"city": "Mumbai", "timestamp": "2026-01-29T12:44:13.402721", "temp": 30.99, "temp_min": 27.94, "temp_max": 30.99, "humidity": 40, "pressure": 1014, "rain_1h": 0, "rain_3h": 0, "wind_speed": 4.12, "clouds": 0, "weather": "Smoke", "description": "smoke", "collected_at": "2026-01-29T12:44:17.607028"}
{"city": "Chennai", "timestamp": "2026-01-29T12:44:13.791145", "temp": 28.39, "temp_min": 27.83, "temp_max": 29.57, "humidity": 60, "pressure": 1016, "rain_1h": 0, "rain_3h": 0, "wind_speed": 5.14, "clouds": 40, "weather": "Haze", "description": "haze", "collected_at": "2026-01-29T12:44:17.607042"}
{"city": "Bangalore", "timestamp": "2026-01-29T12:44:14.197339", "temp": 25.79, "temp_min": 24.64, "temp_max": 26.4, "humidity": 44, "pressure": 1015, "rain_1h": 0, "rain_3h": 0, "wind_speed": 10.28, "clouds": 0, "weather": "Clear", "description": "clear sky", "collected_at": "2026-01-29T12:44:17.607076"}
{"city": "Kolkata", "timestamp": "2026-01-29T12:44:14.601080", "temp": 25.97, "temp_min": 25.97, "temp_max": 25.97, "humidity": 36, "pressure": 1015, "rain_1h": 0, "rain_3h": 0, "wind_speed": 4.12, "clouds": 0, "weather": "Haze", "description": "haze", "collected_at": "2026-01-29T12:44:17.607085"}
{"city": "Pune", "timestamp": "2026-01-29T12:44:15.010885", "temp": 26.89, "temp_min": 26.89, "temp_max": 26.89, "humidity": 42, "pressure": 1015, "rain_1h": 0, "rain_3h": 0, "wind_speed": 3.86, "clouds": 82, "weather": "Clouds", "description": "broken clouds", "collected_at": "2026-01-29T12:44:17.607094"}
{"city": "Hyderabad", "timestamp": "2026-01-29T12:44:15.465795", "temp": 27.23, "temp_min": 27.23, "temp_max": 28.73, "humidity": 44, "pressure": 1015, "rain_1h": 0, "rain_3h": 0, "wind_speed": 5.14, "clouds": 40, "weather": "Haze", "description": "haze", "collected_at": "2026-01-29T12:44:17.607102"}
{"city": "Ahmedabad", "timestamp": "2026-01-29T12:44:15.907409", "temp": 23.02, "temp_min": 23.02, "temp_max": 23.02, "humidity": 40, "pressure": 1017, "rain_1h": 0, "rain_3h": 0, "wind_speed": 4.12, "clouds": 99, "weather": "Smoke", "description": "smoke", "collected_at": "2026-01-29T12:44:17.607110"}
{"city": "Coimbatore", "timestamp": "2026-01-29T12:44:16.333172", "temp": 27.88, "temp_min": 27.88, "temp_max": 27.88, "humidity": 39, "pressure": 1015, "rain_1h": 0, "rain_3h": 0, "wind_speed": 3.6, "clouds": 40, "weather": "Haze", "description": "haze", "collected_at": "2026-01-29T12:44:17.607118"}
{"city": "Madurai", "timestamp": "2026-01-29T12:44:16.741327", "temp": 30.01, "temp_min": 30.01, "temp_max": 30.01, "humidity": 51, "pressure": 1014, "rain_1h": 0, "rain_3h": 0, "wind_speed": 5.14, "clouds": 20, "weather": "Haze", "description": "haze", "collected_at": "2026-01-29T12:44:17.607126"}
{"city": "Visakhapatnam", "timestamp": "2026-01-29T12:44:17.150997", "temp": 28.94, "temp_min": 28.94, "temp_max": 28.94, "humidity": 51, "pressure": 1015, "rain_1h": 0, "rain_3h": 0, "wind_speed": 4.12, "clouds": 20, "weather": "Haze", "description": "haze", "collected_at": "2026-01-29T12:44:17.607134"}
{"city": "Vijayawada", "timestamp": "2026-01-29T12:44:17.587273", "temp": 26.97, "temp_min": 26.97, "temp_max": 26.97, "humidity": 57, "pressure": 1015, "rain_1h": 0, "rain_3h": 0, "wind_speed": 2.06, "clouds": 40, "weather": "Haze", "description": "haze", "collected_at": "2026-01-29T12:44:17.607141"}
{"city": "Delhi", "timestamp": "2026-01-29T12:44:45.060715", "temp": 13.05, "temp_min": 13.05, "temp_max": 13.05, "humidity": 88, "pressure": 1020, "rain_1h": 0, "rain_3h": 0, "wind_speed": 3.09, "clouds": 20, "weather": "Mist", "description": "mist", "collected_at": "2026-01-29T12:44:54.743690"}
{"city": "Mumbai", "timestamp": "2026-01-29T12:44:45.451368", "temp": 30.99, "temp_min": 27.94, "temp_max": 30.99, "humidity": 40, "pressure": 1014, "rain_1h": 0, "rain_3h": 0, "wind_speed": 4.12, "clouds": 0, "weather": "Smoke", "description": "smoke", "collected_at": "2026-01-29T12:44:54.743806"}
{"city": "Chennai", "timestamp": "2026-01-29T12:44:45.864899", "temp": 28.39, "temp_min": 27.83, "temp_max": 29.57, "humidity": 60, "pressure": 1016, "rain_1h": 0, "rain_3h": 0, "wind_speed": 5.14, "clouds": 40, "weather": "Haze", "description": "haze", "collected_at": "2026-01-29T12:44:54.743848"}
{"city": "Bangalore", "timestamp": "2026-01-29T12:44:46.287139", "temp": 25.79, "temp_min": 24.64, "temp_max": 26.4, "humidity": 44, "pressure": 1015, "rain_1h": 0, "rain_3h": 0, "wind_speed": 10.28, "clouds": 0, "weather": "Clear", "description": "clear sky", "collected_at": "2026-01-29T12:44:54.743879"}
{"city": "Kolkata", "timestamp": "2026-01-29T12:44:46.707214", "temp": 25.97, "temp_min": 25.97, "temp_max": 25.97, "humidity": 36, "pressure": 1015, "rain_1h": 0, "rain_3h": 0, "wind_speed": 4.12, "clouds": 0, "weather": "Haze", "description": "haze", "collected_at": "2026-01-29T12:44:54.743907"}
{"city": "Pune", "timestamp": "2026-01-29T12:44:47.801616", "temp": 26.89, "temp_min": 26.89, "temp_max": 26.89, "humidity": 42, "pressure": 1015, "rain_1h": 0, "rain_3h": 0, "wind_speed": 3.86, "clouds": 82, "weather": "Clouds", "description": "broken clouds", "collected_at": "2026-01-29T12:44:54.743935"}
{"city": "Hyderabad", "timestamp": "2026-01-29T12:44:48.892138", "temp": 27.23, "temp_min": 27.23, "temp_max": 28.73, "humidity": 44, "pressure": 1015, "rain_1h": 0, "rain_3h": 0, "wind_speed": 5.14, "clouds": 40, "weather": "Haze", "description": "haze", "collected_at": "2026-01-29T12:44:54.743961"}
{"city": "Ahmedabad", "timestamp": "2026-01-29T12:44:50.051872", "temp": 23.02, "temp_min": 23.02, "temp_max": 23.02, "humidity": 40, "pressure": 1017, "rain_1h": 0, "rain_3h": 0, "wind_speed": 4.12, "clouds": 99, "weather": "Smoke", "description": "smoke", "collected_at": "2026-01-29T12:44:54.743986"}
{"city": "Coimbatore", "timestamp": "2026-01-29T12:44:51.105085", "temp": 27.88, "temp_min": 27.88, "temp_max": 27.88, "humidity": 39, "pressure": 1015, "rain_1h": 0, "rain_3h": 0, "wind_speed": 3.6, "clouds": 40, "weather": "Haze", "description": "haze", "collected_at": "2026-01-29T12:44:54.744011"}
{"city": "Madurai", "timestamp": "2026-01-29T12:44:52.336290", "temp": 30.01, "temp_min": 30.01, "temp_max": 30.01, "humidity": 51, "pressure": 1014, "rain_1h": 0, "rain_3h": 0, "wind_speed": 5.14, "clouds": 20, "weather": "Haze", "description": "haze", "collected_at": "2026-01-29T12:44:54.744035"}
{"city": "Visakhapatnam", "timestamp": "2026-01-29T12:44:53.501277", "temp": 28.94, "temp_min": 28.94, "temp_max": 28.94, "humidity": 51, "pressure": 1015, "rain_1h": 0, "rain_3h": 0, "wind_speed": 4.12, "clouds": 20, "weather": "Haze", "description": "haze", "collected_at": "2026-01-29T12:44:54.744061"}
{"city": "Vijayawada", "timestamp": "2026-01-29T12:44:54.694538", "temp": 26.97, "temp_min": 26.97, "temp_max": 26.97, "humidity": 57, "pressure": 1015, "rain_1h": 0, "rain_3h": 0, "wind_speed": 2.06, "clouds": 40, "weather": "Haze", "description": "haze", "collected_at": "2026-01-29T12:44:54.744086"}
{"city": "Delhi", "timestamp": "2026-01-29T12:45:20.781212", "temp": 13.05, "temp_min": 13.05, "temp_max": 13.05, "humidity": 88, "pressure": 1020, "rain_1h": 0, "rain_3h": 0, "wind_speed": 3.09, "clouds": 20, "weather": "Mist", "description": "mist", "collected_at": "2026-01-29T12:45:25.417758"}
{"city": "Mumbai", "timestamp": "2026-01-29T12:45:21.202222", "temp": 30.99, "temp_min": 27.94, "temp_max": 30.99, "humidity": 40, "pressure": 1014, "rain_1h": 0, "rain_3h": 0, "wind_speed": 4.12, "clouds": 0, "weather": "Smoke", "description": "smoke", "collected_at": "2026-01-29T12:45:25.417789"}
{"city": "Chennai", "timestamp": "2026-01-29T12:45:21.631593", "temp": 28.39, "temp_min": 27.83, "temp_max": 29.57, "humidity": 60, "pressure": 1016, "rain_1h": 0, "rain_3h": 0, "wind_speed": 5.14, "clouds": 40, "weather": "Haze", "description": "haze", "collected_at": "2026-01-29T12:45:25.417804"}
{"city": "Bangalore", "timestamp": "2026-01-29T12:45:22.074224", "temp": 25.79, "temp_min": 24.64, "temp_max": 26.4, "humidity": 44, "pressure": 1015, "rain_1h": 0, "rain_3h": 0, "wind_speed": 10.28, "clouds": 0, "weather": "Clear", "description": "clear sky", "collected_at": "2026-01-29T12:45:25.417842"}
{"city": "Kolkata", "timestamp": "2026-01-29T12:45:22.480686", "temp": 25.97, "temp_min": 25.97, "temp_max": 25.97, "humidity": 36, "pressure": 1015, "rain_1h": 0, "rain_3h": 0, "wind_speed": 4.12, "clouds": 0, "weather": "Haze", "description": "haze", "collected_at": "2026-01-29T12:45:25.417852"}
{"city": "Pune", "timestamp": "2026-01-29T12:45:22.906948", "temp": 26.89, "temp_min": 26.89, "temp_max": 26.89, "humidity": 42, "pressure": 1015, "rain_1h": 0, "rain_3h": 0, "wind_speed": 3.86, "clouds": 82, "weather": "Clouds", "description": "broken clouds", "collected_at": "2026-01-29T12:45:25.417862"}
{"city": "Hyderabad", "timestamp": "2026-01-29T12:45:23.331221", "temp": 27.23, "temp_min": 27.23, "temp_max": 28.73, "humidity": 44, "pressure": 1015, "rain_1h": 0, "rain_3h": 0, "wind_speed": 5.14, "clouds": 40, "weather": "Haze", "description": "haze", "collected_at": "2026-01-29T12:45:25.417871"}
{"city": "Ahmedabad", "timestamp": "2026-01-29T12:45:23.746958", "temp": 23.02, "temp_min": 23.02, "temp_max": 23.02, "humidity": 40, "pressure": 1017, "rain_1h": 0, "rain_3h": 0, "wind_speed": 4.12, "clouds": 99, "weather": "Smoke", "description": "smoke", "collected_at": "2026-01-29T12:45:25.417879"}
{"city": "Coimbatore", "timestamp": "2026-01-29T12:45:24.150789", "temp": 27.88, "temp_min": 27.88, "temp_max": 27.88, "humidity": 39, "pressure": 1015, "rain_1h": 0, "rain_3h": 0, "wind_speed": 3.6, "clouds": 40, "weather": "Haze", "description": "haze", "collected_at": "2026-01-29T12:45:25.417896"}
{"city": "Madurai", "timestamp": "2026-01-29T12:45:24.560283", "temp": 30.01, "temp_min": 30.01, "temp_max": 30.01, "humidity": 51, "pressure": 1014, "rain_1h": 0, "rain_3h": 0, "wind_speed": 5.14, "clouds": 20, "weather": "Haze", "description": "haze", "collected_at": "2026-01-29T12:45:25.417904"}
{"city": "Visakhapatnam", "timestamp": "2026-01-29T12:45:24.970214", "temp": 28.94, "temp_min": 28.94, "temp_max": 28.94, "humidity": 51, "pressure": 1015, "rain_1h": 0, "rain_3h": 0, "wind_speed": 4.12, "clouds": 20, "weather": "Haze", "description": "haze", "collected_at": "2026-01-29T12:45:25.417911"}
{"city": "Vijayawada", "timestamp": "2026-01-29T12:45:25.400511", "temp": 26.97, "temp_min": 26.97, "temp_max": 26.97, "humidity": 57, "pressure": 1015, "rain_1h": 0, "rain_3h": 0, "wind_speed": 2.06, "clouds": 40, "weather": "Haze", "description": "haze", "collected_at": "2026-01-29T12:45:25.417919"}
{"city": "Delhi", "timestamp": "2026-01-29T12:46:22.953926", "temp": 13.05, "temp_min": 13.05, "temp_max": 13.05, "humidity": 88, "pressure": 1020, "rain_1h": 0, "rain_3h": 0, "wind_speed": 3.09, "clouds": 20, "weather": "Mist", "description": "mist", "collected_at": "2026-01-29T12:46:29.688522"}
{"city": "Mumbai", "timestamp": "2026-01-29T12:46:23.340787", "temp": 30.99, "temp_min": 27.94, "temp_max": 30.99, "humidity": 40, "pressure": 1014, "rain_1h": 0, "rain_3h": 0, "wind_speed": 4.12, "clouds": 0, "weather": "Smoke", "description": "smoke", "collected_at": "2026-01-29T12:46:29.688577"}
{"city": "Chennai", "timestamp": "2026-01-29T12:46:23.766868", "temp": 28.39, "temp_min": 27.83, "temp_max": 29.57, "humidity": 60, "pressure": 1016, "rain_1h": 0, "rain_3h": 0, "wind_speed": 5.14, "clouds": 40, "weather": "Haze", "description": "haze", "collected_at": "2026-01-29T12:46:29.688608"}
{"city": "Bangalore", "timestamp": "2026-01-29T12:46:24.171172", "temp": 25.79, "temp_min": 24.64, "temp_max": 26.4, "humidity": 44, "pressure": 1015, "rain_1h": 0, "rain_3h": 0, "wind_speed": 10.28, "clouds": 0, "weather": "Clear", "description": "clear sky", "collected_at": "2026-01-29T12:46:29.688628"}
{"city": "Kolkata", "timestamp": "2026-01-29T12:46:24.560670", "temp": 25.97, "temp_min": 25.97, "temp_max": 25.97, "humidity": 36, "pressure": 1015, "rain_1h": 0, "rain_3h": 0, "wind_speed": 4.12, "clouds": 0, "weather": "Haze", "description": "haze", "collected_at": "2026-01-29T12:46:29.688647"}
{"city": "Pune", "timestamp": "2026-01-29T12:46:24.986616", "temp": 26.89, "temp_min": 26.89, "temp_max": 26.89, "humidity": 42, "pressure": 1015, "rain_1h": 0, "rain_3h": 0, "wind_speed": 3.86, "clouds": 82, "weather": "Clouds", "description": "broken clouds", "collected_at": "2026-01-29T12:46:29.688665"}
{"city": "Hyderabad", "timestamp": "2026-01-29T12:46:25.413393", "temp": 27.23, "temp_min": 27.23, "temp_max": 28.73, "humidity": 44, "pressure": 1015, "rain_1h": 0, "rain_3h": 0, "wind_speed": 5.14, "clouds": 40, "weather": "Haze", "description": "haze", "collected_at": "2026-01-29T12:46:29.688682"}
{"city": "Ahmedabad", "timestamp": "2026-01-29T12:46:25.830968", "temp": 23.02, "temp_min": 23.02, "temp_max": 23.02, "humidity": 40, "pressure": 1017, "rain_1h": 0, "rain_3h": 0, "wind_speed": 4.12, "clouds": 99, "weather": "Smoke", "description": "smoke", "collected_at": "2026-01-29T12:46:29.688698"}
{"city": "Coimbatore", "timestamp": "2026-01-29T12:46:26.536538", "temp": 27.88, "temp_min": 27.88, "temp_max": 27.88, "humidity": 39, "pressure": 1015, "rain_1h": 0, "rain_3h": 0, "wind_speed": 3.6, "clouds": 40, "weather": "Haze", "description": "haze", "collected_at": "2026-01-29T12:46:29.688714"}
{"city": "Madurai", "timestamp": "2026-01-29T12:46:27.575474", "temp": 30.01, "temp_min": 30.01, "temp_max": 30.01, "humidity": 51, "pressure": 1014, "rain_1h": 0, "rain_3h": 0, "wind_speed": 5.14, "clouds": 20, "weather": "Haze", "description": "haze", "collected_at": "2026-01-29T12:46:29.688730"}
{"city": "Visakhapatnam", "timestamp": "2026-01-29T12:46:28.657603", "temp": 28.94, "temp_min": 28.94, "temp_max": 28.94, "humidity": 51, "pressure": 1015, "rain_1h": 0, "rain_3h": 0, "wind_speed": 4.12, "clouds": 20, "weather": "Haze", "description": "haze", "collected_at": "2026-01-29T12:46:29.688746"}
{"city": "Vijayawada", "timestamp": "2026-01-29T12:46:29.644888", "temp": 26.97, "temp_min": 26.97, "temp_max": 26.97, "humidity": 57, "pressure": 1015, "rain_1h": 0, "rain_3h": 0, "wind_speed": 2.06, "clouds": 40, "weather": "Haze", "description": "haze", "collected_at": "2026-01-29T12:46:29.688761"}
{"city": "Delhi", "timestamp": "2026-01-29T12:47:10.173273", "temp": 13.05, "temp_min": 13.05, "temp_max": 13.05, "humidity": 88, "pressure": 1020, "rain_1h": 0, "rain_3h": 0, "wind_speed": 3.09, "clouds": 20, "weather": "Mist", "description": "mist", "collected_at": "2026-01-29T12:47:14.829801"}
{"city": "Mumbai", "timestamp": "2026-01-29T12:47:10.570948", "temp": 30.99, "temp_min": 27.94, "temp_max": 30.99, "humidity": 40, "pressure": 1014, "rain_1h": 0, "rain_3h": 0, "wind_speed": 4.12, "clouds": 0, "weather": "Smoke", "description": "smoke", "collected_at": "2026-01-29T12:47:14.829830"}
{"city": "Chennai", "timestamp": "2026-01-29T12:47:10.978803", "temp": 28.39, "temp_min": 27.83, "temp_max": 29.57, "humidity": 60, "pressure": 1016, "rain_1h": 0, "rain_3h": 0, "wind_speed": 5.14, "clouds": 40, "weather": "Haze", "description": "haze", "collected_at": "2026-01-29T12:47:14.829845"}
{"city": "Bangalore", "timestamp": "2026-01-29T12:47:11.388729", "temp": 25.79, "temp_min": 24.64, "temp_max": 26.4, "humidity": 44, "pressure": 1015, "rain_1h": 0, "rain_3h": 0, "wind_speed": 10.28, "clouds": 0, "weather": "Clear", "description": "clear sky", "collected_at": "2026-01-29T12:47:14.829854"}
{"city": "Kolkata", "timestamp": "2026-01-29T12:47:11.794644", "temp": 25.97, "temp_min": 25.97, "temp_max": 25.97, "humidity": 36, "pressure": 1015, "rain_1h": 0, "rain_3h": 0, "wind_speed": 4.12, "clouds": 0, "weather": "Haze", "description": "haze", "collected_at": "2026-01-29T12:47:14.829863"}
{"city": "Pune", "timestamp": "2026-01-29T12:47:12.194185", "temp": 26.89, "temp_min": 26.89, "temp_max": 26.89, "humidity": 42, "pressure": 1015, "rain_1h": 0, "rain_3h": 0, "wind_speed": 3.86, "clouds": 82, "weather": "Clouds", "description": "broken clouds", "collected_at": "2026-01-29T12:47:14.829870"}
{"city": "Hyderabad", "timestamp": "2026-01-29T12:47:12.616687", "temp": 27.23, "temp_min": 27.23, "temp_max": 28.73, "humidity": 44, "pressure": 1015, "rain_1h": 0, "rain_3h": 0, "wind_speed": 5.14, "clouds": 40, "weather": "Haze", "description": "haze", "collected_at": "2026-01-29T12:47:14.829879"}
{"city": "Ahmedabad", "timestamp": "2026-01-29T12:47:13.036598", "temp": 23.02, "temp_min": 23.02, "temp_max": 23.02, "humidity": 40, "pressure": 1017, "rain_1h": 0, "rain_3h": 0, "wind_speed": 4.12, "clouds": 99, "weather": "Smoke", "description": "smoke", "collected_at": "2026-01-29T12:47:14.829887"}
{"city": "Coimbatore", "timestamp": "2026-01-29T12:47:13.478886", "temp": 27.88, "temp_min": 27.88, "temp_max": 27.88, "humidity": 39, "pressure": 1015, "rain_1h": 0, "rain_3h": 0, "wind_speed": 3.6, "clouds": 40, "weather": "Haze", "description": "haze", "collected_at": "2026-01-29T12:47:14.829894"}
{"city": "Madurai", "timestamp": "2026-01-29T12:47:13.901418", "temp": 30.01, "temp_min": 30.01, "temp_max": 30.01, "humidity": 51, "pressure": 1014, "rain_1h": 0, "rain_3h": 0, "wind_speed": 5.14, "clouds": 20, "weather": "Haze", "description": "haze", "collected_at": "2026-01-29T12:47:14.829903"}
{"city": "Visakhapatnam", "timestamp": "2026-01-29T12:47:14.341368", "temp": 28.94, "temp_min": 28.94, "temp_max": 28.94, "humidity": 51, "pressure": 1015, "rain_1h": 0, "rain_3h": 0, "wind_speed": 4.12, "clouds": 20, "weather": "Haze", "description": "haze", "collected_at": "2026-01-29T12:47:14.829910"}
{"city": "Vijayawada", "timestamp": "2026-01-29T12:47:14.794769", "temp": 26.97, "temp_min": 26.97, "temp_max": 26.97, "humidity": 57, "pressure": 1015, "rain_1h": 0, "rain_3h": 0, "wind_speed": 2.06, "clouds": 40, "weather": "Haze", "description": "haze", "collected_at": "2026-01-29T12:47:14.829918"}
{"city": "Delhi", "timestamp": "2026-01-29T12:47:48.860924", "temp": 13.05, "temp_min": 13.05, "temp_max": 13.05, "humidity": 88, "pressure": 1020, "rain_1h": 0, "rain_3h": 0, "wind_speed": 3.09, "clouds": 20, "weather": "Mist", "description": "mist", "collected_at": "2026-01-29T12:47:59.859910"}
{"city": "Mumbai", "timestamp": "2026-01-29T12:47:49.860366", "temp": 30.99, "temp_min": 27.94, "temp_max": 30.99, "humidity": 40, "pressure": 1014, "rain_1h": 0, "rain_3h": 0, "wind_speed": 4.12, "clouds": 0, "weather": "Smoke", "description": "smoke", "collected_at": "2026-01-29T12:47:59.860019"}
{"city": "Chennai", "timestamp": "2026-01-29T12:47:50.853056", "temp": 28.39, "temp_min": 27.83, "temp_max": 29.57, "humidity": 60, "pressure": 1016, "rain_1h": 0, "rain_3h": 0, "wind_speed": 5.14, "clouds": 40, "weather": "Haze", "description": "haze", "collected_at": "2026-01-29T12:47:59.860077"}
{"city": "Bangalore", "timestamp": "2026-01-29T12:47:51.930551", "temp": 25.79, "temp_min": 24.64, "temp_max": 26.4, "humidity": 44, "pressure": 1015, "rain_1h": 0, "rain_3h": 0, "wind_speed": 10.28, "clouds": 0, "weather": "Clear", "description": "clear sky", "collected_at": "2026-01-29T12:47:59.860121"}
{"city": "Kolkata", "timestamp": "2026-01-29T12:47:52.820225", "temp": 25.97, "temp_min": 25.97, "temp_max": 25.97, "humidity": 36, "pressure": 1015, "rain_1h": 0, "rain_3h": 0, "wind_speed": 4.12, "clouds": 0, "weather": "Haze", "description": "haze", "collected_at": "2026-01-29T12:47:59.860162"}
{"city": "Pune", "timestamp": "2026-01-29T12:47:53.852439", "temp": 26.89, "temp_min": 26.89, "temp_max": 26.89, "humidity": 42, "pressure": 1015, "rain_1h": 0, "rain_3h": 0, "wind_speed": 3.86, "clouds": 82, "weather": "Clouds", "description": "broken clouds", "collected_at": "2026-01-29T12:47:59.860200"}
{"city": "Hyderabad", "timestamp": "2026-01-29T12:47:54.870065", "temp": 27.23, "temp_min": 27.23, "temp_max": 28.73, "humidity": 44, "pressure": 1015, "rain_1h": 0, "rain_3h": 0, "wind_speed": 5.14, "clouds": 40, "weather": "Haze", "description": "haze", "collected_at": "2026-01-29T12:47:59.860238"}
{"city": "Ahmedabad", "timestamp": "2026-01-29T12:47:55.805359", "temp": 23.02, "temp_min": 23.02, "temp_max": 23.02, "humidity": 40, "pressure": 1017, "rain_1h": 0, "rain_3h": 0, "wind_speed": 4.12, "clouds": 99, "weather": "Smoke", "description": "smoke", "collected_at": "2026-01-29T12:47:59.860275"}
{"city": "Coimbatore", "timestamp": "2026-01-29T12:47:56.834860", "temp": 27.88, "temp_min": 27.88, "temp_max": 27.88, "humidity": 39, "pressure": 1015, "rain_1h": 0, "rain_3h": 0, "wind_speed": 3.6, "clouds": 40, "weather": "Haze", "description": "haze", "collected_at": "2026-01-29T12:47:59.860310"}
{"city": "Madurai", "timestamp": "2026-01-29T12:47:57.880443", "temp": 30.01, "temp_min": 30.01, "temp_max": 30.01, "humidity": 51, "pressure": 1014, "rain_1h": 0, "rain_3h": 0, "wind_speed": 5.14, "clouds": 20, "weather": "Haze", "description": "haze", "collected_at": "2026-01-29T12:47:59.860346"}
{"city": "Visakhapatnam", "timestamp": "2026-01-29T12:47:58.740285", "temp": 28.94, "temp_min": 28.94, "temp_max": 28.94, "humidity": 51, "pressure": 1015, "rain_1h": 0, "rain_3h": 0, "wind_speed": 4.12, "clouds": 20, "weather": "Haze", "description": "haze", "collected_at": "2026-01-29T12:47:59.860445"}
{"city": "Vijayawada", "timestamp": "2026-01-29T12:47:59.761518", "temp": 26.97, "temp_min": 26.97, "temp_max": 26.97, "humidity": 57, "pressure": 1015, "rain_1h": 0, "rain_3h": 0, "wind_speed": 2.06, "clouds": 40, "weather": "Haze", "description": "haze", "collected_at": "2026-01-29T12:47:59.860484"}
{"city": "Delhi", "timestamp": "2026-01-29T12:49:20.341855", "temp": 13.05, "temp_min": 13.05, "temp_max": 13.05, "humidity": 88, "pressure": 1020, "rain_1h": 0, "rain_3h": 0, "wind_speed": 3.09, "clouds": 20, "weather": "Mist", "description": "mist", "collected_at": "2026-01-29T12:49:25.045444"}
{"city": "Mumbai", "timestamp": "2026-01-29T12:49:20.770999", "temp": 30.99, "temp_min": 27.94, "temp_max": 30.99, "humidity": 40, "pressure": 1014, "rain_1h": 0, "rain_3h": 0, "wind_speed": 4.12, "clouds": 0, "weather": "Smoke", "description": "smoke", "collected_at": "2026-01-29T12:49:25.045483"}
{"city": "Chennai", "timestamp": "2026-01-29T12:49:21.209983", "temp": 28.39, "temp_min": 27.83, "temp_max": 29.57, "humidity": 60, "pressure": 1016, "rain_1h": 0, "rain_3h": 0, "wind_speed": 5.14, "clouds": 40, "weather": "Haze", "description": "haze", "collected_at": "2026-01-29T12:49:25.045497"}
{"city": "Bangalore", "timestamp": "2026-01-29T12:49:21.653891", "temp": 25.79, "temp_min": 24.64, "temp_max": 26.4, "humidity": 44, "pressure": 1015, "rain_1h": 0, "rain_3h": 0, "wind_speed": 10.28, "clouds": 0, "weather": "Clear", "description": "clear sky", "collected_at": "2026-01-29T12:49:25.045508"}
{"city": "Kolkata", "timestamp": "2026-01-29T12:49:22.100731", "temp": 25.97, "temp_min": 25.97, "temp_max": 25.97, "humidity": 36, "pressure": 1015, "rain_1h": 0, "rain_3h": 0, "wind_speed": 4.12, "clouds": 0, "weather": "Haze", "description": "haze", "collected_at": "2026-01-29T12:49:25.045517"}
{"city": "Pune", "timestamp": "2026-01-29T12:49:22.499524", "temp": 26.89, "temp_min": 26.89, "temp_max": 26.89, "humidity": 42, "pressure": 1015, "rain_1h": 0, "rain_3h": 0, "wind_speed": 3.86, "clouds": 82, "weather": "Clouds", "description": "broken clouds", "collected_at": "2026-01-29T12:49:25.045525"}
{"city": "Hyderabad", "timestamp": "2026-01-29T12:49:22.911323", "temp": 27.23, "temp_min": 27.23, "temp_max": 28.73, "humidity": 44, "pressure": 1015, "rain_1h": 0, "rain_3h": 0, "wind_speed": 5.14, "clouds": 40, "weather": "Haze", "description": "haze", "collected_at": "2026-01-29T12:49:25.045534"}
{"city": "Ahmedabad", "timestamp": "2026-01-29T12:49:23.339279", "temp": 23.02, "temp_min": 23.02, "temp_max": 23.02, "humidity": 40, "pressure": 1017, "rain_1h": 0, "rain_3h": 0, "wind_speed": 4.12, "clouds": 99, "weather": "Smoke", "description": "smoke", "collected_at": "2026-01-29T12:49:25.045541"}
{"city": "Coimbatore", "timestamp": "2026-01-29T12:49:23.749489", "temp": 27.88, "temp_min": 27.88, "temp_max": 27.88, "humidity": 39, "pressure": 1015, "rain_1h": 0, "rain_3h": 0, "wind_speed": 3.6, "clouds": 40, "weather": "Haze", "description": "haze", "collected_at": "2026-01-29T12:49:25.045549"}
{"city": "Madurai", "timestamp": "2026-01-29T12:49:24.151270", "temp": 30.01, "temp_min": 30.01, "temp_max": 30.01, "humidity": 51, "pressure": 1014, "rain_1h": 0, "rain_3h": 0, "wind_speed": 5.14, "clouds": 20, "weather": "Haze", "description": "haze", "collected_at": "2026-01-29T12:49:25.045557"}
{"city": "Visakhapatnam", "timestamp": "2026-01-29T12:49:24.558271", "temp": 28.94, "temp_min": 28.94, "temp_max": 28.94, "humidity": 51, "pressure": 1015, "rain_1h": 0, "rain_3h": 0, "wind_speed": 4.12, "clouds": 20, "weather": "Haze", "description": "haze", "collected_at": "2026-01-29T12:49:25.045565"}
{"city": "Vijayawada", "timestamp": "2026-01-29T12:49:24.965261", "temp": 26.97, "temp_min": 26.97, "temp_max": 26.97, "humidity": 57, "pressure": 1015, "rain_1h": 0, "rain_3h": 0, "wind_speed": 2.06, "clouds": 40, "weather": "Haze", "description": "haze", "collected_at": "2026-01-29T12:49:25.045573"}
